openstack_bucket_retention/__init__.py
openstack_bucket_retention/cli.py
openstack_bucket_retention/core.py
openstack_bucket_retention-0.2.0.dist-info/entry_points.txt
openstack_bucket_retention-0.2.0.dist-info/LICENSE
openstack_bucket_retention-0.2.0.dist-info/WHEEL
openstack_bucket_retention-0.2.0.dist-info/METADATA
openstack_bucket_retention-0.2.0.dist-info/RECORD
