Metadata-Version: 2.1
Name: openstack-bucket-retention
Version: 0.2.0
Summary: Openstack Bucket (Container) Retention
Home-page: https://github.com/f9n/openstack-bucket-retention
License: GPL-3.0
Author: Fatih Sarhan
Author-email: f9n@protonmail.com
Requires-Python: >=3.9,<4.0
Classifier: License :: OSI Approved :: GNU General Public License v3 (GPLv3)
Classifier: Programming Language :: Python :: 3
Classifier: Programming Language :: Python :: 3.10
Classifier: Programming Language :: Python :: 3.9
Requires-Dist: click (>=8.0.3,<9.0.0)
Requires-Dist: python-keystoneclient (>=4.4.0,<5.0.0)
Requires-Dist: python-swiftclient (>=3.13.0,<4.0.0)
Project-URL: Repository, https://github.com/f9n/openstack-bucket-retention
